{"cameraMode":{"drawMode":0,"name":"Shaded","section":"Shading Mode"},"sceneLighting":true,"audioPlay":false,"sceneViewState":{"showFog":true,"showMaterialUpdate":false,"showSkybox":true,"showFlares":true,"showImageEffects":true,"showParticleSystems":true},"in2DMode":false,"pivot":{"x":-3.417245864868164,"y":5.724983215332031,"z":-2.778524875640869},"rotation":{"x":-0.20962589979171754,"y":-0.17722371220588685,"z":0.03866451233625412,"w":-0.9608123898506165},"size":1.0271319150924683,"orthographic":false}